addemongo-0.1.0.dist-info/METADATA
addemongo-0.1.0.dist-info/WHEEL
addemongo/__init__.py
addemongo/_base_client.py
addemongo/_motor/__init__.py
addemongo/_motor/_client.py
addemongo/_pymongo/__init__.py
addemongo/_pymongo/_client.py
addemongo/_types.py
addemongo/builders/__init__.py
addemongo/builders/aggregation.py
addemongo/builders/query.py
addemongo/connection.py
addemongo/models/__init__.py
addemongo/models/pagination.py
addemongo-0.1.0.dist-info/RECORD
