Metadata-Version: 2.1
Name: AddeMongo
Version: 0.1.0
Summary: Private mongo repository for Addebitare company
License: MIT
Project-URL: Github, https://github.com/biellSilva/addemongo
Requires-Python: >=3.11
Requires-Dist: pymongo>=4.7.1
Requires-Dist: motor>=3.4.0
Requires-Dist: pydantic>=2.7.1
